configai/__init__.py
configai/compiler.py
configai/model_wrapper.py
configai-0.1.1.dist-info/licenses/LICENSE
configai-0.1.1.dist-info/METADATA
configai-0.1.1.dist-info/WHEEL
configai-0.1.1.dist-info/top_level.txt
configai-0.1.1.dist-info/RECORD
