Metadata-Version: 2.4
Name: configai
Version: 0.1.1
Summary: PyTorch to HLS deployment compiler powered by Stream-HLS
Home-page: https://github.com/ayushkumar1808/Stream-HLS
Author: Ayush Kumar
Author-email: Ayush Kumar <ayush@example.com>
License: MIT
Project-URL: Homepage, https://github.com/ayushkumar1808/Stream-HLS
Project-URL: Repository, https://github.com/ayushkumar1808/Stream-HLS
Keywords: pytorch,hls,fpga,compiler,mlir,configai
Classifier: Development Status :: 3 - Alpha
Classifier: Intended Audience :: Developers
Classifier: Topic :: Software Development :: Compilers
Classifier: License :: OSI Approved :: MIT License
Classifier: Programming Language :: Python :: 3
Requires-Python: >=3.8
License-File: LICENSE
Requires-Dist: torch>=2.0.0
Requires-Dist: numpy>=1.20.0
Provides-Extra: dev
Requires-Dist: pytest>=7.0.0; extra == "dev"
Requires-Dist: black>=22.0.0; extra == "dev"
Requires-Dist: flake8>=4.0.0; extra == "dev"
Dynamic: author
Dynamic: home-page
Dynamic: license-file
Dynamic: requires-python
